{
  "client": true,
  "id": "1.2.3",
  "manifests": [
    {
      "assetHash": "4759bad2824e419da9db32861fcdc3a274336532",
      "assetIndex": "pre-1.6",
      "downloads": "a28ae36ed4a8150800d19a128c172c1de0d82792",
      "downloadsId": 1,
      "hash": "6c06fcbac55906c96a850f28876788797e0146be",
      "time": "2012-03-01T22:00:00+00:00",
      "type": "release",
      "url": "https://skyrising.github.io/mc-versions/manifest/6/c/06fcbac55906c96a850f28876788797e0146be/1.2.3.json"
    }
  ],
  "next": [
    "1.2.4"
  ],
  "previous": [
    "1.2.2"
  ],
  "protocol": {
    "type": "modern",
    "version": 28
  },
  "releaseTime": "2012-03-02T08:36:00+00:00",
  "server": false,
  "world": {
    "format": "anvil"
  }
}