{
  "$schema": "https://skyrising.github.io/mc-versions/schemas/version.json",
  "client": true,
  "displayVersion": "1.20 Pre-release 6",
  "downloads": {
    "client": {
      "sha1": "cc1332993000882883e40cf28bc41f2d01e2ed0d",
      "size": 23011874,
      "url": "https://piston-data.mojang.com/v1/objects/cc1332993000882883e40cf28bc41f2d01e2ed0d/client.jar"
    },
    "client_mappings": {
      "sha1": "a83ba44876be0c1861e2ca4eb6e2e713bab300cd",
      "size": 7993190,
      "url": "https://piston-data.mojang.com/v1/objects/a83ba44876be0c1861e2ca4eb6e2e713bab300cd/client.txt"
    },
    "server": {
      "sha1": "c737b7411fc0b60426a9feca83d09d63f4a86f27",
      "size": 47775744,
      "url": "https://piston-data.mojang.com/v1/objects/c737b7411fc0b60426a9feca83d09d63f4a86f27/server.jar"
    },
    "server_mappings": {
      "sha1": "c77ccb042ced83e08727a05f0e289e4a4f981b39",
      "size": 6146664,
      "url": "https://piston-data.mojang.com/v1/objects/c77ccb042ced83e08727a05f0e289e4a4f981b39/server.txt"
    }
  },
  "id": "1.20-pre6",
  "libraries": [
    "com.github.oshi:oshi-core:6.2.2",
    "com.google.code.gson:gson:2.10",
    "com.google.guava:failureaccess:1.0.1",
    "com.google.guava:guava:31.1-jre",
    "com.ibm.icu:icu4j:71.1",
    "com.mojang:authlib:4.0.43",
    "com.mojang:blocklist:1.0.10",
    "com.mojang:brigadier:1.1.8",
    "com.mojang:datafixerupper:6.0.8",
    "com.mojang:logging:1.1.1",
    "com.mojang:patchy:2.2.10",
    "com.mojang:text2speech:1.17.9",
    "commons-codec:commons-codec:1.15",
    "commons-io:commons-io:2.11.0",
    "commons-logging:commons-logging:1.2",
    "io.netty:netty-buffer:4.1.82.Final",
    "io.netty:netty-codec:4.1.82.Final",
    "io.netty:netty-common:4.1.82.Final",
    "io.netty:netty-handler:4.1.82.Final",
    "io.netty:netty-resolver:4.1.82.Final",
    "io.netty:netty-transport-classes-epoll:4.1.82.Final",
    "io.netty:netty-transport-native-unix-common:4.1.82.Final",
    "io.netty:netty-transport:4.1.82.Final",
    "it.unimi.dsi:fastutil:8.5.9",
    "net.java.dev.jna:jna-platform:5.12.1",
    "net.java.dev.jna:jna:5.12.1",
    "net.sf.jopt-simple:jopt-simple:5.0.4",
    "org.apache.commons:commons-compress:1.21",
    "org.apache.commons:commons-lang3:3.12.0",
    "org.apache.httpcomponents:httpclient:4.5.13",
    "org.apache.httpcomponents:httpcore:4.4.15",
    "org.apache.logging.log4j:log4j-api:2.19.0",
    "org.apache.logging.log4j:log4j-core:2.19.0",
    "org.apache.logging.log4j:log4j-slf4j2-impl:2.19.0",
    "org.joml:joml:1.10.5",
    "org.lwjgl:lwjgl-glfw:3.3.1",
    "org.lwjgl:lwjgl-jemalloc:3.3.1",
    "org.lwjgl:lwjgl-openal:3.3.1",
    "org.lwjgl:lwjgl-opengl:3.3.1",
    "org.lwjgl:lwjgl-stb:3.3.1",
    "org.lwjgl:lwjgl-tinyfd:3.3.1",
    "org.lwjgl:lwjgl:3.3.1",
    "org.slf4j:slf4j-api:2.0.1"
  ],
  "manifests": [
    {
      "assetHash": "22bc98cde01bd58c7d7f928162d2960b8d9c0f06",
      "assetIndex": "5",
      "downloads": "c12f1382c12813fd8bfc7395234f3d0573752387",
      "downloadsId": 1,
      "hash": "e67f81ebbb92a5f0f77d5d0a04eec91d44509460",
      "lastModified": "2024-10-10T13:16:02+00:00",
      "time": "2023-05-25T12:22:00+00:00",
      "type": "snapshot",
      "url": "https://skyrising.github.io/mc-versions/manifest/e/6/7f81ebbb92a5f0f77d5d0a04eec91d44509460/1.20-pre6.json"
    },
    {
      "assetHash": "e489826a4b755e70eeda872f46fe084fccacfd68",
      "assetIndex": "5",
      "downloads": "c12f1382c12813fd8bfc7395234f3d0573752387",
      "downloadsId": 1,
      "hash": "fb8831bcaa4f0968099ee7983c50b9c6d5ad298f",
      "lastModified": "2024-10-08T13:35:10+00:00",
      "time": "2023-05-25T12:22:00+00:00",
      "type": "snapshot",
      "url": "https://skyrising.github.io/mc-versions/manifest/f/b/8831bcaa4f0968099ee7983c50b9c6d5ad298f/1.20-pre6.json"
    },
    {
      "assetHash": "37d057c5a3633bea6e3246a2875c31ced1642d40",
      "assetIndex": "5",
      "downloads": "c12f1382c12813fd8bfc7395234f3d0573752387",
      "downloadsId": 1,
      "hash": "1132d04347f0442dd5bbc9e90d4733ebdd79a684",
      "lastModified": "2024-10-02T14:49:28+00:00",
      "time": "2023-05-25T12:22:00+00:00",
      "type": "snapshot",
      "url": "https://skyrising.github.io/mc-versions/manifest/1/1/32d04347f0442dd5bbc9e90d4733ebdd79a684/1.20-pre6.json"
    },
    {
      "assetHash": "deff28247ad5a294b5edcab128507ea9b9a98c6d",
      "assetIndex": "5",
      "downloads": "c12f1382c12813fd8bfc7395234f3d0573752387",
      "downloadsId": 1,
      "hash": "17d551a1ea753d94b4bc019a126d0a158a60228f",
      "lastModified": "2024-09-18T12:56:47+00:00",
      "time": "2023-05-25T12:22:00+00:00",
      "type": "snapshot",
      "url": "https://skyrising.github.io/mc-versions/manifest/1/7/d551a1ea753d94b4bc019a126d0a158a60228f/1.20-pre6.json"
    },
    {
      "assetHash": "9ee5b32d87acded8f2d3d57ceec589ee5243ea61",
      "assetIndex": "5",
      "downloads": "c12f1382c12813fd8bfc7395234f3d0573752387",
      "downloadsId": 1,
      "hash": "32d6226abe6c9e1059fc4fc129a03c0c7148ae5b",
      "lastModified": "2024-09-11T13:33:09+00:00",
      "time": "2023-05-25T12:22:00+00:00",
      "type": "snapshot",
      "url": "https://skyrising.github.io/mc-versions/manifest/3/2/d6226abe6c9e1059fc4fc129a03c0c7148ae5b/1.20-pre6.json"
    },
    {
      "assetHash": "32c7a27ebcbce1cd5649fc237ccbc65dcf1d79fa",
      "assetIndex": "5",
      "downloads": "c12f1382c12813fd8bfc7395234f3d0573752387",
      "downloadsId": 1,
      "hash": "714e909d6c999e13bbe13a73def8d6252a7e1fc7",
      "lastModified": "2024-09-04T12:58:56+00:00",
      "time": "2023-05-25T12:22:00+00:00",
      "type": "snapshot",
      "url": "https://skyrising.github.io/mc-versions/manifest/7/1/4e909d6c999e13bbe13a73def8d6252a7e1fc7/1.20-pre6.json"
    },
    {
      "assetHash": "102454a05c5e871fe2370467fcca6f85b29c1b66",
      "assetIndex": "5",
      "downloads": "c12f1382c12813fd8bfc7395234f3d0573752387",
      "downloadsId": 1,
      "hash": "11ff69c72bce293c5632e8b320f86fc53168ac16",
      "lastModified": "2024-08-28T12:43:36+00:00",
      "time": "2023-05-25T12:22:00+00:00",
      "type": "snapshot",
      "url": "https://skyrising.github.io/mc-versions/manifest/1/1/ff69c72bce293c5632e8b320f86fc53168ac16/1.20-pre6.json"
    },
    {
      "assetHash": "c9305ae3fc6ab8ca96d8906b333eb9a0668f0a88",
      "assetIndex": "5",
      "downloads": "c12f1382c12813fd8bfc7395234f3d0573752387",
      "downloadsId": 1,
      "hash": "7dabde3612960b152cbfcd0b7bee500cb15210b1",
      "lastModified": "2024-08-21T13:26:08+00:00",
      "time": "2023-05-25T12:22:00+00:00",
      "type": "snapshot",
      "url": "https://skyrising.github.io/mc-versions/manifest/7/d/abde3612960b152cbfcd0b7bee500cb15210b1/1.20-pre6.json"
    },
    {
      "assetHash": "2dc7096b288a21c5f1bb7c17a8a7132cb32ca6cd",
      "assetIndex": "5",
      "downloads": "c12f1382c12813fd8bfc7395234f3d0573752387",
      "downloadsId": 1,
      "hash": "ed475bc6d02956abc0661cf3806c7af4cbd50988",
      "lastModified": "2024-08-15T12:54:13+00:00",
      "time": "2023-05-25T12:22:00+00:00",
      "type": "snapshot",
      "url": "https://skyrising.github.io/mc-versions/manifest/e/d/475bc6d02956abc0661cf3806c7af4cbd50988/1.20-pre6.json"
    },
    {
      "assetHash": "7c7e4c4d92ffd684d5673a07632c5ca1b7d44de0",
      "assetIndex": "5",
      "downloads": "c12f1382c12813fd8bfc7395234f3d0573752387",
      "downloadsId": 1,
      "hash": "7d13042a68876b8b6d7f531bac403a35cbe524ab",
      "lastModified": "2024-08-08T12:46:57+00:00",
      "time": "2023-05-25T12:22:00+00:00",
      "type": "snapshot",
      "url": "https://skyrising.github.io/mc-versions/manifest/7/d/13042a68876b8b6d7f531bac403a35cbe524ab/1.20-pre6.json"
    },
    {
      "assetHash": "a3b8b3d3169cfad8aa54367be13ab59c143bbccb",
      "assetIndex": "5",
      "downloads": "c12f1382c12813fd8bfc7395234f3d0573752387",
      "downloadsId": 1,
      "hash": "f68a831747d0e7eba861502cc8839fc2eff778c0",
      "lastModified": "2024-08-07T09:51:03+00:00",
      "time": "2023-05-25T12:22:00+00:00",
      "type": "snapshot",
      "url": "https://skyrising.github.io/mc-versions/manifest/f/6/8a831747d0e7eba861502cc8839fc2eff778c0/1.20-pre6.json"
    },
    {
      "assetHash": "2ee890f5542de15bb7f3f64965ff494d9af4bcfc",
      "assetIndex": "5",
      "downloads": "c12f1382c12813fd8bfc7395234f3d0573752387",
      "downloadsId": 1,
      "hash": "5f15e3ad4bc39118e588da8200728fa343bf92f9",
      "lastModified": "2024-06-13T08:59:30+00:00",
      "time": "2023-05-25T12:22:00+00:00",
      "type": "snapshot",
      "url": "https://skyrising.github.io/mc-versions/manifest/5/f/15e3ad4bc39118e588da8200728fa343bf92f9/1.20-pre6.json"
    },
    {
      "assetHash": "b443f4810a71d32a0773c9f484f36727f8c9cfad",
      "assetIndex": "5",
      "downloads": "c12f1382c12813fd8bfc7395234f3d0573752387",
      "downloadsId": 1,
      "hash": "9abbb7e03f1770ec75557cd61bb4993883d718b9",
      "lastModified": "2024-06-10T12:48:37+00:00",
      "time": "2023-05-25T12:22:00+00:00",
      "type": "snapshot",
      "url": "https://skyrising.github.io/mc-versions/manifest/9/a/bbb7e03f1770ec75557cd61bb4993883d718b9/1.20-pre6.json"
    },
    {
      "assetHash": "769a3b72e5e90256a4d730fdb9d002b4bb93f57d",
      "assetIndex": "5",
      "downloads": "c12f1382c12813fd8bfc7395234f3d0573752387",
      "downloadsId": 1,
      "hash": "ae52962d239e09218035048af47783792995e49f",
      "lastModified": "2024-06-07T12:12:10+00:00",
      "time": "2023-05-25T12:22:00+00:00",
      "type": "snapshot",
      "url": "https://skyrising.github.io/mc-versions/manifest/a/e/52962d239e09218035048af47783792995e49f/1.20-pre6.json"
    },
    {
      "assetHash": "3852581f33892e6d0a6005b9518b55e9914c6c11",
      "assetIndex": "5",
      "downloads": "c12f1382c12813fd8bfc7395234f3d0573752387",
      "downloadsId": 1,
      "hash": "84d5ff974b59581d1eec28020bb795af41e24974",
      "lastModified": "2024-06-05T09:01:08+00:00",
      "time": "2023-05-25T12:22:00+00:00",
      "type": "snapshot",
      "url": "https://skyrising.github.io/mc-versions/manifest/8/4/d5ff974b59581d1eec28020bb795af41e24974/1.20-pre6.json"
    },
    {
      "assetHash": "325d7e7274bcbb84a60aad3153e15c8a9ff01d2c",
      "assetIndex": "5",
      "downloads": "c12f1382c12813fd8bfc7395234f3d0573752387",
      "downloadsId": 1,
      "hash": "f0e90392347deda4bc1b65a346a2c364a6642ff8",
      "lastModified": "2024-05-31T12:08:13+00:00",
      "time": "2023-05-25T12:22:00+00:00",
      "type": "snapshot",
      "url": "https://skyrising.github.io/mc-versions/manifest/f/0/e90392347deda4bc1b65a346a2c364a6642ff8/1.20-pre6.json"
    },
    {
      "assetHash": "c3ab01c02c2d43b2fac88952d973792ea0a8244e",
      "assetIndex": "5",
      "downloads": "c12f1382c12813fd8bfc7395234f3d0573752387",
      "downloadsId": 1,
      "hash": "4180ec3a9a03a114da4b593178002e277420af56",
      "lastModified": "2024-05-29T12:21:45+00:00",
      "time": "2023-05-25T12:22:00+00:00",
      "type": "snapshot",
      "url": "https://skyrising.github.io/mc-versions/manifest/4/1/80ec3a9a03a114da4b593178002e277420af56/1.20-pre6.json"
    },
    {
      "assetHash": "c1dc5934ce71dd8854ec5055dd9d67df42cf6ee4",
      "assetIndex": "5",
      "downloads": "c12f1382c12813fd8bfc7395234f3d0573752387",
      "downloadsId": 1,
      "hash": "26068fb63bf8cc2911467a357f92306a3bfdff0f",
      "lastModified": "2024-05-22T13:26:23+00:00",
      "time": "2023-05-25T12:22:00+00:00",
      "type": "snapshot",
      "url": "https://skyrising.github.io/mc-versions/manifest/2/6/068fb63bf8cc2911467a357f92306a3bfdff0f/1.20-pre6.json"
    },
    {
      "assetHash": "62c3c060293dd9f5b99cc07638c42168d1803a3a",
      "assetIndex": "5",
      "downloads": "c12f1382c12813fd8bfc7395234f3d0573752387",
      "downloadsId": 1,
      "hash": "1b4f03ce2977d2a1da906785bee8596ad4300695",
      "lastModified": "2024-05-15T12:37:46+00:00",
      "time": "2023-05-25T12:22:00+00:00",
      "type": "snapshot",
      "url": "https://skyrising.github.io/mc-versions/manifest/1/b/4f03ce2977d2a1da906785bee8596ad4300695/1.20-pre6.json"
    },
    {
      "assetHash": "9558aac63e62e87eccf0313a65b6e22cc08de21d",
      "assetIndex": "5",
      "downloads": "c12f1382c12813fd8bfc7395234f3d0573752387",
      "downloadsId": 1,
      "hash": "4a45f3e1af501ad8e3a07891715b6a93d08e62cf",
      "lastModified": "2024-05-10T12:26:59+00:00",
      "time": "2023-05-25T12:22:00+00:00",
      "type": "snapshot",
      "url": "https://skyrising.github.io/mc-versions/manifest/4/a/45f3e1af501ad8e3a07891715b6a93d08e62cf/1.20-pre6.json"
    },
    {
      "assetHash": "44dcbb2d4327933c7f04d594184a337c4481c908",
      "assetIndex": "5",
      "downloads": "c12f1382c12813fd8bfc7395234f3d0573752387",
      "downloadsId": 1,
      "hash": "d3f0a330d19496d834aa12c4881467d123bf1eb0",
      "lastModified": "2024-05-03T12:23:21+00:00",
      "time": "2023-05-25T12:22:00+00:00",
      "type": "snapshot",
      "url": "https://skyrising.github.io/mc-versions/manifest/d/3/f0a330d19496d834aa12c4881467d123bf1eb0/1.20-pre6.json"
    },
    {
      "assetHash": "fed13e2fb0ea8b9a3e757709bc734ddcf8bb75e7",
      "assetIndex": "5",
      "downloads": "c12f1382c12813fd8bfc7395234f3d0573752387",
      "downloadsId": 1,
      "hash": "a7c658ea30622b269359228e05d95f06c3ec817f",
      "lastModified": "2024-04-29T13:00:01+00:00",
      "time": "2023-05-25T12:22:00+00:00",
      "type": "snapshot",
      "url": "https://skyrising.github.io/mc-versions/manifest/a/7/c658ea30622b269359228e05d95f06c3ec817f/1.20-pre6.json"
    },
    {
      "assetHash": "bcff100c21067e1537bb4f41fa280126f9b75959",
      "assetIndex": "5",
      "downloads": "c12f1382c12813fd8bfc7395234f3d0573752387",
      "downloadsId": 1,
      "hash": "ac55cf82f9ea0dda601d6cfda65670ec7532d90e",
      "lastModified": "2024-04-26T10:55:05+00:00",
      "time": "2023-05-25T12:22:00+00:00",
      "type": "snapshot",
      "url": "https://skyrising.github.io/mc-versions/manifest/a/c/55cf82f9ea0dda601d6cfda65670ec7532d90e/1.20-pre6.json"
    },
    {
      "assetHash": "b47e3e8537e29635222cdda2913df24e50e1a161",
      "assetIndex": "5",
      "downloads": "c12f1382c12813fd8bfc7395234f3d0573752387",
      "downloadsId": 1,
      "hash": "1f414a708516165358ac7f286abbd4c02c6bdeed",
      "lastModified": "2024-04-23T12:31:18+00:00",
      "time": "2023-05-25T12:22:00+00:00",
      "type": "snapshot",
      "url": "https://skyrising.github.io/mc-versions/manifest/1/f/414a708516165358ac7f286abbd4c02c6bdeed/1.20-pre6.json"
    },
    {
      "assetHash": "1f1911f06781880313f3456fac583cd2f63ed0f0",
      "assetIndex": "5",
      "downloads": "c12f1382c12813fd8bfc7395234f3d0573752387",
      "downloadsId": 1,
      "hash": "ef26f4160ac564e65b79c76f60dd7d94560472bd",
      "lastModified": "2024-04-22T13:53:08+00:00",
      "time": "2023-05-25T12:22:00+00:00",
      "type": "snapshot",
      "url": "https://skyrising.github.io/mc-versions/manifest/e/f/26f4160ac564e65b79c76f60dd7d94560472bd/1.20-pre6.json"
    },
    {
      "assetHash": "de273278c1a9b51bde7bdc25cd16faab6b08b5bd",
      "assetIndex": "5",
      "downloads": "c12f1382c12813fd8bfc7395234f3d0573752387",
      "downloadsId": 1,
      "hash": "d8095f4d0808efbf97de62be1eda4eff14d1a2a7",
      "lastModified": "2024-04-19T13:22:19+00:00",
      "time": "2023-05-25T12:22:00+00:00",
      "type": "snapshot",
      "url": "https://skyrising.github.io/mc-versions/manifest/d/8/095f4d0808efbf97de62be1eda4eff14d1a2a7/1.20-pre6.json"
    },
    {
      "assetHash": "4715406a85f856fe93bf3b0b24df0ec8b5d505bb",
      "assetIndex": "5",
      "downloads": "c12f1382c12813fd8bfc7395234f3d0573752387",
      "downloadsId": 1,
      "hash": "08823d0a7e29e129a2f4a8687306b7b7f268d154",
      "lastModified": "2024-04-18T12:03:30+00:00",
      "time": "2023-05-25T12:22:00+00:00",
      "type": "snapshot",
      "url": "https://skyrising.github.io/mc-versions/manifest/0/8/823d0a7e29e129a2f4a8687306b7b7f268d154/1.20-pre6.json"
    },
    {
      "assetHash": "c64d31bacb21eaec58e5dece3ac90e8903cbddf7",
      "assetIndex": "5",
      "downloads": "c12f1382c12813fd8bfc7395234f3d0573752387",
      "downloadsId": 1,
      "hash": "dcc6b7cdfd5219f0bac585318bd5df739385a814",
      "lastModified": "2024-04-17T12:15:35+00:00",
      "time": "2023-05-25T12:22:00+00:00",
      "type": "snapshot",
      "url": "https://skyrising.github.io/mc-versions/manifest/d/c/c6b7cdfd5219f0bac585318bd5df739385a814/1.20-pre6.json"
    },
    {
      "assetHash": "f6b4824a50c421432a1f72b0a9b367cdf9897a15",
      "assetIndex": "5",
      "downloads": "c12f1382c12813fd8bfc7395234f3d0573752387",
      "downloadsId": 1,
      "hash": "42f3bc6438af6e9e67f6640483cc85ed9819323a",
      "lastModified": "2024-04-16T12:10:40+00:00",
      "time": "2023-05-25T12:22:00+00:00",
      "type": "snapshot",
      "url": "https://skyrising.github.io/mc-versions/manifest/4/2/f3bc6438af6e9e67f6640483cc85ed9819323a/1.20-pre6.json"
    },
    {
      "assetHash": "15c0fd8e23de5bd3c62b1a22db09a8e6c27d1488",
      "assetIndex": "5",
      "downloads": "c12f1382c12813fd8bfc7395234f3d0573752387",
      "downloadsId": 1,
      "hash": "a97e83bb5d13739f7bc79f4093b10b6fbe6d28a6",
      "lastModified": "2024-04-15T13:03:38+00:00",
      "time": "2023-05-25T12:22:00+00:00",
      "type": "snapshot",
      "url": "https://skyrising.github.io/mc-versions/manifest/a/9/7e83bb5d13739f7bc79f4093b10b6fbe6d28a6/1.20-pre6.json"
    },
    {
      "assetHash": "7f0e965c270e811b2c61fd2d093442dfa783fe75",
      "assetIndex": "5",
      "downloads": "c12f1382c12813fd8bfc7395234f3d0573752387",
      "downloadsId": 1,
      "hash": "dd9b67b9a9c2de52892fe655f0822b3dabe11d34",
      "lastModified": "2024-04-10T12:57:42+00:00",
      "time": "2023-05-25T12:22:00+00:00",
      "type": "snapshot",
      "url": "https://skyrising.github.io/mc-versions/manifest/d/d/9b67b9a9c2de52892fe655f0822b3dabe11d34/1.20-pre6.json"
    },
    {
      "assetHash": "893f34e4432f759ef137b221de6915ed74048aaa",
      "assetIndex": "5",
      "downloads": "c12f1382c12813fd8bfc7395234f3d0573752387",
      "downloadsId": 1,
      "hash": "bd4a8c85cc4847b5ca70531579c5b6c9d91210a2",
      "lastModified": "2024-04-03T12:19:29+00:00",
      "time": "2023-05-25T12:22:00+00:00",
      "type": "snapshot",
      "url": "https://skyrising.github.io/mc-versions/manifest/b/d/4a8c85cc4847b5ca70531579c5b6c9d91210a2/1.20-pre6.json"
    },
    {
      "assetHash": "45400d7671172429031ee49847e9108da3d61da0",
      "assetIndex": "5",
      "downloads": "c12f1382c12813fd8bfc7395234f3d0573752387",
      "downloadsId": 1,
      "hash": "7ee3a570959973369c79b100ab2bdca49dbf5c61",
      "lastModified": "2024-04-01T08:51:42+00:00",
      "time": "2023-05-25T12:22:00+00:00",
      "type": "snapshot",
      "url": "https://skyrising.github.io/mc-versions/manifest/7/e/e3a570959973369c79b100ab2bdca49dbf5c61/1.20-pre6.json"
    },
    {
      "assetHash": "38deaa95b91b2b5dbbdebd62a8329efcf0fd3c90",
      "assetIndex": "5",
      "downloads": "c12f1382c12813fd8bfc7395234f3d0573752387",
      "downloadsId": 1,
      "hash": "5ab313f1f81eede8137619adbc730a421b238e63",
      "lastModified": "2024-03-27T14:59:17+00:00",
      "time": "2023-05-25T12:22:00+00:00",
      "type": "snapshot",
      "url": "https://skyrising.github.io/mc-versions/manifest/5/a/b313f1f81eede8137619adbc730a421b238e63/1.20-pre6.json"
    },
    {
      "assetHash": "b7822a859498601f89b4e2fbda47f11f3ce7f432",
      "assetIndex": "5",
      "downloads": "c12f1382c12813fd8bfc7395234f3d0573752387",
      "downloadsId": 1,
      "hash": "0565eae0dc01f7c81e03e6d0c55d27b5c3b996a7",
      "lastModified": "2024-03-20T14:51:44+00:00",
      "time": "2023-05-25T12:22:00+00:00",
      "type": "snapshot",
      "url": "https://skyrising.github.io/mc-versions/manifest/0/5/65eae0dc01f7c81e03e6d0c55d27b5c3b996a7/1.20-pre6.json"
    },
    {
      "assetHash": "6fa5d3fcb2364c62b7f340830413708252cc2717",
      "assetIndex": "5",
      "downloads": "c12f1382c12813fd8bfc7395234f3d0573752387",
      "downloadsId": 1,
      "hash": "f9379ac5e9f35e8df5066d1ab392a90296995e42",
      "lastModified": "2024-03-14T14:32:12+00:00",
      "time": "2023-05-25T12:22:00+00:00",
      "type": "snapshot",
      "url": "https://skyrising.github.io/mc-versions/manifest/f/9/379ac5e9f35e8df5066d1ab392a90296995e42/1.20-pre6.json"
    },
    {
      "assetHash": "49a6178e63dc0dc6aed858d111d1a906eb3d9091",
      "assetIndex": "5",
      "downloads": "c12f1382c12813fd8bfc7395234f3d0573752387",
      "downloadsId": 1,
      "hash": "6bea8de2e531ee614861050933c9d63e8c8a461d",
      "lastModified": "2024-03-06T10:47:47+00:00",
      "time": "2023-05-25T12:22:00+00:00",
      "type": "snapshot",
      "url": "https://skyrising.github.io/mc-versions/manifest/6/b/ea8de2e531ee614861050933c9d63e8c8a461d/1.20-pre6.json"
    },
    {
      "assetHash": "dd5c945894ca239138141c1e7eee5cdc0ce0f338",
      "assetIndex": "5",
      "downloads": "c12f1382c12813fd8bfc7395234f3d0573752387",
      "downloadsId": 1,
      "hash": "e239d8d5c41362d3b1f8d8e75933aadf8409e7b7",
      "lastModified": "2024-02-28T13:19:41+00:00",
      "time": "2023-05-25T12:22:00+00:00",
      "type": "snapshot",
      "url": "https://skyrising.github.io/mc-versions/manifest/e/2/39d8d5c41362d3b1f8d8e75933aadf8409e7b7/1.20-pre6.json"
    },
    {
      "assetHash": "0ec9e71b6a0433431b680a79976df6bea59ae99b",
      "assetIndex": "5",
      "downloads": "c12f1382c12813fd8bfc7395234f3d0573752387",
      "downloadsId": 1,
      "hash": "6d18196903c1cdff05268cb77cedb6965676be89",
      "lastModified": "2024-02-14T14:34:26+00:00",
      "time": "2023-05-25T12:22:00+00:00",
      "type": "snapshot",
      "url": "https://skyrising.github.io/mc-versions/manifest/6/d/18196903c1cdff05268cb77cedb6965676be89/1.20-pre6.json"
    },
    {
      "assetHash": "82eb5c515ef0a8ba1fb3aad3f3ca453a37f06384",
      "assetIndex": "5",
      "downloads": "c12f1382c12813fd8bfc7395234f3d0573752387",
      "downloadsId": 1,
      "hash": "18ff3182795155a7695a875540dc389efd3abc23",
      "lastModified": "2024-02-07T15:02:11+00:00",
      "time": "2023-05-25T12:22:00+00:00",
      "type": "snapshot",
      "url": "https://skyrising.github.io/mc-versions/manifest/1/8/ff3182795155a7695a875540dc389efd3abc23/1.20-pre6.json"
    },
    {
      "assetHash": "c0424926b17d3969dbc93ad106cc26486fbaabeb",
      "assetIndex": "5",
      "downloads": "c12f1382c12813fd8bfc7395234f3d0573752387",
      "downloadsId": 1,
      "hash": "cc513a20498ab9b51de29b51b45c1de204c9b572",
      "lastModified": "2024-02-01T13:08:00+00:00",
      "time": "2023-05-25T12:22:00+00:00",
      "type": "snapshot",
      "url": "https://skyrising.github.io/mc-versions/manifest/c/c/513a20498ab9b51de29b51b45c1de204c9b572/1.20-pre6.json"
    },
    {
      "assetHash": "0ee929f32706b44bf18add1266be2c3a8bc5d2ec",
      "assetIndex": "5",
      "downloads": "c12f1382c12813fd8bfc7395234f3d0573752387",
      "downloadsId": 1,
      "hash": "ddb630ab7ea193a562f7b8b1af977b49b8c63c0d",
      "lastModified": "2024-01-31T13:28:32+00:00",
      "time": "2023-05-25T12:22:00+00:00",
      "type": "snapshot",
      "url": "https://skyrising.github.io/mc-versions/manifest/d/d/b630ab7ea193a562f7b8b1af977b49b8c63c0d/1.20-pre6.json"
    },
    {
      "assetHash": "a7134aaac1c69b1e85ba193f8138a1cab73ed741",
      "assetIndex": "5",
      "downloads": "c12f1382c12813fd8bfc7395234f3d0573752387",
      "downloadsId": 1,
      "hash": "a690b4626b37f295fe17635892e440c533776927",
      "lastModified": "2024-01-24T14:05:37+00:00",
      "time": "2023-05-25T12:22:00+00:00",
      "type": "snapshot",
      "url": "https://skyrising.github.io/mc-versions/manifest/a/6/90b4626b37f295fe17635892e440c533776927/1.20-pre6.json"
    },
    {
      "assetHash": "04d15f210d729d5fd8a45ba2baeebd9f5f8d3b7f",
      "assetIndex": "5",
      "downloads": "c12f1382c12813fd8bfc7395234f3d0573752387",
      "downloadsId": 1,
      "hash": "42a5242a77d0cec32027f97a834c2159daec0889",
      "lastModified": "2024-01-18T12:53:06+00:00",
      "time": "2023-05-25T12:22:00+00:00",
      "type": "snapshot",
      "url": "https://skyrising.github.io/mc-versions/manifest/4/2/a5242a77d0cec32027f97a834c2159daec0889/1.20-pre6.json"
    },
    {
      "assetHash": "9ffd3b09c03f24c5901154e018112719f349d723",
      "assetIndex": "5",
      "downloads": "c12f1382c12813fd8bfc7395234f3d0573752387",
      "downloadsId": 1,
      "hash": "51d6e6b609ddf5c0bc7adf4ac4082697eb6cfa67",
      "lastModified": "2024-01-17T14:38:46+00:00",
      "time": "2023-05-25T12:22:00+00:00",
      "type": "snapshot",
      "url": "https://skyrising.github.io/mc-versions/manifest/5/1/d6e6b609ddf5c0bc7adf4ac4082697eb6cfa67/1.20-pre6.json"
    },
    {
      "assetHash": "47f698efd9a7b3e287aa6ae72ed8d6c7543702b1",
      "assetIndex": "5",
      "downloads": "c12f1382c12813fd8bfc7395234f3d0573752387",
      "downloadsId": 1,
      "hash": "046d2e682b37ba1f732a081f88ada66f846b37df",
      "lastModified": "2023-12-18T13:55:21+00:00",
      "time": "2023-05-25T12:22:00+00:00",
      "type": "snapshot",
      "url": "https://skyrising.github.io/mc-versions/manifest/0/4/6d2e682b37ba1f732a081f88ada66f846b37df/1.20-pre6.json"
    },
    {
      "assetHash": "40380abf4f9b39abe36f186616543b0b4e4bc88e",
      "assetIndex": "5",
      "downloads": "c12f1382c12813fd8bfc7395234f3d0573752387",
      "downloadsId": 1,
      "hash": "805f3add15b99bb60ed74aaa5976b73d83daf809",
      "lastModified": "2023-12-07T13:04:59+00:00",
      "time": "2023-05-25T12:22:00+00:00",
      "type": "snapshot",
      "url": "https://skyrising.github.io/mc-versions/manifest/8/0/5f3add15b99bb60ed74aaa5976b73d83daf809/1.20-pre6.json"
    },
    {
      "assetHash": "5d7537d4e1104eaa6ca29b3050b167b4a7f5d6ed",
      "assetIndex": "5",
      "downloads": "c12f1382c12813fd8bfc7395234f3d0573752387",
      "downloadsId": 1,
      "hash": "27ca0517d2959be367cead30ef654aef5ba1afec",
      "lastModified": "2023-12-06T14:48:30+00:00",
      "time": "2023-05-25T12:22:00+00:00",
      "type": "snapshot",
      "url": "https://skyrising.github.io/mc-versions/manifest/2/7/ca0517d2959be367cead30ef654aef5ba1afec/1.20-pre6.json"
    },
    {
      "assetHash": "346f40facda7792fa409cf6b1dd1d236e91e1f1b",
      "assetIndex": "5",
      "downloads": "c12f1382c12813fd8bfc7395234f3d0573752387",
      "downloadsId": 1,
      "hash": "00c2aef51438eba5b8bffa71d47bf406825df133",
      "lastModified": "2023-12-05T08:26:27+00:00",
      "time": "2023-05-25T12:22:00+00:00",
      "type": "snapshot",
      "url": "https://skyrising.github.io/mc-versions/manifest/0/0/c2aef51438eba5b8bffa71d47bf406825df133/1.20-pre6.json"
    },
    {
      "assetHash": "d6d6e76c67a153e9abb75596b4c23a3305f20b59",
      "assetIndex": "5",
      "downloads": "c12f1382c12813fd8bfc7395234f3d0573752387",
      "downloadsId": 1,
      "hash": "82110666223ffac434c1aeaf9fdb2ee7ea5a06a4",
      "lastModified": "2023-11-30T13:54:21+00:00",
      "time": "2023-05-25T12:22:00+00:00",
      "type": "snapshot",
      "url": "https://skyrising.github.io/mc-versions/manifest/8/2/110666223ffac434c1aeaf9fdb2ee7ea5a06a4/1.20-pre6.json"
    },
    {
      "assetHash": "1062f888f6f8e0e6cfb6f9a0dacb59c9a46f35c8",
      "assetIndex": "5",
      "downloads": "c12f1382c12813fd8bfc7395234f3d0573752387",
      "downloadsId": 1,
      "hash": "d93864a9619f43ecf18c3f393cd852d7af8292c3",
      "lastModified": "2023-11-28T13:55:57+00:00",
      "time": "2023-05-25T12:22:00+00:00",
      "type": "snapshot",
      "url": "https://skyrising.github.io/mc-versions/manifest/d/9/3864a9619f43ecf18c3f393cd852d7af8292c3/1.20-pre6.json"
    },
    {
      "assetHash": "c4909cce4ee3822b7560c93d9321e8c58b5fa00f",
      "assetIndex": "5",
      "downloads": "c12f1382c12813fd8bfc7395234f3d0573752387",
      "downloadsId": 1,
      "hash": "7389e9abed757333cc8e476510ed0dbd09f585fb",
      "lastModified": "2023-11-27T14:37:22+00:00",
      "time": "2023-05-25T12:22:00+00:00",
      "type": "snapshot",
      "url": "https://skyrising.github.io/mc-versions/manifest/7/3/89e9abed757333cc8e476510ed0dbd09f585fb/1.20-pre6.json"
    },
    {
      "assetHash": "77817a7e3ba88530d8489b9c6c280ec286c6ea9a",
      "assetIndex": "5",
      "downloads": "c12f1382c12813fd8bfc7395234f3d0573752387",
      "downloadsId": 1,
      "hash": "f1a37b766c9a5737596627bb2434ec6ccc98d992",
      "lastModified": "2023-11-22T12:39:41+00:00",
      "time": "2023-05-25T12:22:00+00:00",
      "type": "snapshot",
      "url": "https://skyrising.github.io/mc-versions/manifest/f/1/a37b766c9a5737596627bb2434ec6ccc98d992/1.20-pre6.json"
    },
    {
      "assetHash": "9f5cae8b18a50b398bde215e54c6ee2b135fcc68",
      "assetIndex": "5",
      "downloads": "c12f1382c12813fd8bfc7395234f3d0573752387",
      "downloadsId": 1,
      "hash": "83ad8c32aca2f12727837cef173933c94cc3f670",
      "lastModified": "2023-11-20T15:49:53+00:00",
      "time": "2023-05-25T12:22:00+00:00",
      "type": "snapshot",
      "url": "https://skyrising.github.io/mc-versions/manifest/8/3/ad8c32aca2f12727837cef173933c94cc3f670/1.20-pre6.json"
    },
    {
      "assetHash": "b513497769a18ad280496058a290494a963a5831",
      "assetIndex": "5",
      "downloads": "c12f1382c12813fd8bfc7395234f3d0573752387",
      "downloadsId": 1,
      "hash": "307effd48112dd89774731291f970591ac9e918a",
      "lastModified": "2023-11-16T14:26:38+00:00",
      "time": "2023-05-25T12:22:00+00:00",
      "type": "snapshot",
      "url": "https://skyrising.github.io/mc-versions/manifest/3/0/7effd48112dd89774731291f970591ac9e918a/1.20-pre6.json"
    },
    {
      "assetHash": "0b9d3b6646cb1e3482719b9267ee429dd5e08a1b",
      "assetIndex": "5",
      "downloads": "c12f1382c12813fd8bfc7395234f3d0573752387",
      "downloadsId": 1,
      "hash": "d0f11b67c33edc9c9ff80034aa3beee27333d473",
      "lastModified": "2023-11-08T14:09:21+00:00",
      "time": "2023-05-25T12:22:00+00:00",
      "type": "snapshot",
      "url": "https://skyrising.github.io/mc-versions/manifest/d/0/f11b67c33edc9c9ff80034aa3beee27333d473/1.20-pre6.json"
    },
    {
      "assetHash": "1e14a8e145a7706909bc8126eae8e475d7f9b9ef",
      "assetIndex": "5",
      "downloads": "c12f1382c12813fd8bfc7395234f3d0573752387",
      "downloadsId": 1,
      "hash": "a71f8157bfd20f0365243a05f8daed16f6f5e628",
      "lastModified": "2023-11-01T12:41:00+00:00",
      "time": "2023-05-25T12:22:00+00:00",
      "type": "snapshot",
      "url": "https://skyrising.github.io/mc-versions/manifest/a/7/1f8157bfd20f0365243a05f8daed16f6f5e628/1.20-pre6.json"
    },
    {
      "assetHash": "1b51f68c6f2d8ac4261b4043a6578bd60fd45d5c",
      "assetIndex": "5",
      "downloads": "c12f1382c12813fd8bfc7395234f3d0573752387",
      "downloadsId": 1,
      "hash": "dc55238ebf3dd7e2f3acd9b2db74398bf73beac7",
      "lastModified": "2023-10-26T13:55:05+00:00",
      "time": "2023-05-25T12:22:00+00:00",
      "type": "snapshot",
      "url": "https://skyrising.github.io/mc-versions/manifest/d/c/55238ebf3dd7e2f3acd9b2db74398bf73beac7/1.20-pre6.json"
    },
    {
      "assetHash": "f264804601a22e72b177bed9910ddc4f957eb94e",
      "assetIndex": "5",
      "downloads": "c12f1382c12813fd8bfc7395234f3d0573752387",
      "downloadsId": 1,
      "hash": "50ea4682369da32007bc9eda2ccb3bf9f248bd97",
      "lastModified": "2023-10-25T13:44:37+00:00",
      "time": "2023-05-25T12:22:00+00:00",
      "type": "snapshot",
      "url": "https://skyrising.github.io/mc-versions/manifest/5/0/ea4682369da32007bc9eda2ccb3bf9f248bd97/1.20-pre6.json"
    },
    {
      "assetHash": "11bad809b2805237d72ee3ea536811a3ed7667d9",
      "assetIndex": "5",
      "downloads": "c12f1382c12813fd8bfc7395234f3d0573752387",
      "downloadsId": 1,
      "hash": "f35deddd7c87545828fcb87a341165426c4c859d",
      "lastModified": "2023-10-18T11:59:06+00:00",
      "time": "2023-05-25T12:22:00+00:00",
      "type": "snapshot",
      "url": "https://skyrising.github.io/mc-versions/manifest/f/3/5deddd7c87545828fcb87a341165426c4c859d/1.20-pre6.json"
    },
    {
      "assetHash": "003fdea144ff47942f1c4b56a13884652b7c613f",
      "assetIndex": "5",
      "downloads": "c12f1382c12813fd8bfc7395234f3d0573752387",
      "downloadsId": 1,
      "hash": "560cfdd6326d63ab7dff7bdaa4c2578eb13a91fe",
      "lastModified": "2023-10-11T12:46:33+00:00",
      "time": "2023-05-25T12:22:00+00:00",
      "type": "snapshot",
      "url": "https://skyrising.github.io/mc-versions/manifest/5/6/0cfdd6326d63ab7dff7bdaa4c2578eb13a91fe/1.20-pre6.json"
    },
    {
      "assetHash": "57aaa522552f12c13007f515de7abff9f52bde74",
      "assetIndex": "5",
      "downloads": "c12f1382c12813fd8bfc7395234f3d0573752387",
      "downloadsId": 1,
      "hash": "4d2bd7324f33ee0d9c1a8873db029fdfe2a97d71",
      "lastModified": "2023-10-04T12:57:36+00:00",
      "time": "2023-05-25T12:22:00+00:00",
      "type": "snapshot",
      "url": "https://skyrising.github.io/mc-versions/manifest/4/d/2bd7324f33ee0d9c1a8873db029fdfe2a97d71/1.20-pre6.json"
    },
    {
      "assetHash": "c25bce94cd70da8c60b540606ef405f7c2c72dcf",
      "assetIndex": "5",
      "downloads": "c12f1382c12813fd8bfc7395234f3d0573752387",
      "downloadsId": 1,
      "hash": "102818a0716c0930754be8daea47d82770c2d424",
      "lastModified": "2023-09-21T09:19:51+00:00",
      "time": "2023-05-25T12:22:00+00:00",
      "type": "snapshot",
      "url": "https://skyrising.github.io/mc-versions/manifest/1/0/2818a0716c0930754be8daea47d82770c2d424/1.20-pre6.json"
    },
    {
      "assetHash": "244f3d082015565dcf139d92e7816cd839a6a6e3",
      "assetIndex": "5",
      "downloads": "c12f1382c12813fd8bfc7395234f3d0573752387",
      "downloadsId": 1,
      "hash": "a187370c6d03ce9d4fcffde2bb92cec363068898",
      "lastModified": "2023-09-18T12:43:00+00:00",
      "time": "2023-05-25T12:22:00+00:00",
      "type": "snapshot",
      "url": "https://skyrising.github.io/mc-versions/manifest/a/1/87370c6d03ce9d4fcffde2bb92cec363068898/1.20-pre6.json"
    },
    {
      "assetHash": "7a05724d46b041b5558190bb871de92b62405795",
      "assetIndex": "5",
      "downloads": "c12f1382c12813fd8bfc7395234f3d0573752387",
      "downloadsId": 1,
      "hash": "f4c4d737db523b4d40534ec9485b8e88fc8f6f93",
      "lastModified": "2023-09-15T13:20:15+00:00",
      "time": "2023-05-25T12:22:00+00:00",
      "type": "snapshot",
      "url": "https://skyrising.github.io/mc-versions/manifest/f/4/c4d737db523b4d40534ec9485b8e88fc8f6f93/1.20-pre6.json"
    },
    {
      "assetHash": "40a019d0307f21781739d179a80add22f22a9dd4",
      "assetIndex": "5",
      "downloads": "c12f1382c12813fd8bfc7395234f3d0573752387",
      "downloadsId": 1,
      "hash": "fe1d7120fa214c6af14be1a07b342b72ecde9bcd",
      "lastModified": "2023-09-13T15:18:17+00:00",
      "time": "2023-05-25T12:22:00+00:00",
      "type": "snapshot",
      "url": "https://skyrising.github.io/mc-versions/manifest/f/e/1d7120fa214c6af14be1a07b342b72ecde9bcd/1.20-pre6.json"
    },
    {
      "assetHash": "a72acc61844bbfc743cb0eabfe1c300ae5d7c15f",
      "assetIndex": "5",
      "downloads": "c12f1382c12813fd8bfc7395234f3d0573752387",
      "downloadsId": 1,
      "hash": "2a84c321cfcf2a3d26c6e2e9bbc2f295bb818778",
      "lastModified": "2023-09-12T12:22:36+00:00",
      "time": "2023-05-25T12:22:00+00:00",
      "type": "snapshot",
      "url": "https://skyrising.github.io/mc-versions/manifest/2/a/84c321cfcf2a3d26c6e2e9bbc2f295bb818778/1.20-pre6.json"
    },
    {
      "assetHash": "9767c3c7faa655f0cc4798d30736e1df8d6a710f",
      "assetIndex": "5",
      "downloads": "c12f1382c12813fd8bfc7395234f3d0573752387",
      "downloadsId": 1,
      "hash": "18ac931046495f981dc1aa95d03ea1998406cfb2",
      "lastModified": "2023-09-07T12:51:44+00:00",
      "time": "2023-05-25T12:22:00+00:00",
      "type": "snapshot",
      "url": "https://skyrising.github.io/mc-versions/manifest/1/8/ac931046495f981dc1aa95d03ea1998406cfb2/1.20-pre6.json"
    },
    {
      "assetHash": "664c2ee90f8b4a9ac7555bf031ff6c9dc5e60579",
      "assetIndex": "5",
      "downloads": "c12f1382c12813fd8bfc7395234f3d0573752387",
      "downloadsId": 1,
      "hash": "1b13d3a0ef3ba18aa6adc38ffb5c82ccb3a74a6d",
      "lastModified": "2023-09-04T12:35:15+00:00",
      "time": "2023-05-25T12:22:00+00:00",
      "type": "snapshot",
      "url": "https://skyrising.github.io/mc-versions/manifest/1/b/13d3a0ef3ba18aa6adc38ffb5c82ccb3a74a6d/1.20-pre6.json"
    },
    {
      "assetHash": "1a8e4fcd47eb2b8a8e910b2a7d2bf6262169d7bc",
      "assetIndex": "5",
      "downloads": "c12f1382c12813fd8bfc7395234f3d0573752387",
      "downloadsId": 1,
      "hash": "dd7b992244dd05f99b4ea81d8184831cf8f58ca7",
      "lastModified": "2023-08-30T11:33:57+00:00",
      "time": "2023-05-25T12:22:00+00:00",
      "type": "snapshot",
      "url": "https://skyrising.github.io/mc-versions/manifest/d/d/7b992244dd05f99b4ea81d8184831cf8f58ca7/1.20-pre6.json"
    },
    {
      "assetHash": "0e20dc78553f6850535c579b751f5758d0969a39",
      "assetIndex": "5",
      "downloads": "c12f1382c12813fd8bfc7395234f3d0573752387",
      "downloadsId": 1,
      "hash": "996319ad8989ebc6f7a74b95fa394422a34f825b",
      "lastModified": "2023-08-17T11:33:42+00:00",
      "time": "2023-05-25T12:22:00+00:00",
      "type": "snapshot",
      "url": "https://skyrising.github.io/mc-versions/manifest/9/9/6319ad8989ebc6f7a74b95fa394422a34f825b/1.20-pre6.json"
    },
    {
      "assetHash": "38b21373c374be43d150bd00709f7c5abf480028",
      "assetIndex": "5",
      "downloads": "c12f1382c12813fd8bfc7395234f3d0573752387",
      "downloadsId": 1,
      "hash": "d4793dcc273481948dd5dea5c9c144d9b8bd827f",
      "lastModified": "2023-07-31T11:40:23+00:00",
      "time": "2023-05-25T12:22:00+00:00",
      "type": "snapshot",
      "url": "https://skyrising.github.io/mc-versions/manifest/d/4/793dcc273481948dd5dea5c9c144d9b8bd827f/1.20-pre6.json"
    },
    {
      "assetHash": "9d58fdd2538c6877fb5c5c558ebc60ee0b6d0e84",
      "assetIndex": "5",
      "downloads": "c12f1382c12813fd8bfc7395234f3d0573752387",
      "downloadsId": 1,
      "hash": "6212df5bb211304d5cb11ac35f29b1bf8467438b",
      "lastModified": "2023-06-12T13:36:00+00:00",
      "time": "2023-05-25T12:22:00+00:00",
      "type": "snapshot",
      "url": "https://skyrising.github.io/mc-versions/manifest/6/2/12df5bb211304d5cb11ac35f29b1bf8467438b/1.20-pre6.json"
    },
    {
      "assetHash": "edc6213221c780c6f44ec687084046200189c605",
      "assetIndex": "5",
      "downloads": "c12f1382c12813fd8bfc7395234f3d0573752387",
      "downloadsId": 1,
      "hash": "67c149d8f119b951e46b1e7d16c25facb7ce2ad4",
      "lastModified": "2023-06-09T14:24:50+00:00",
      "time": "2023-05-25T12:22:00+00:00",
      "type": "snapshot",
      "url": "https://skyrising.github.io/mc-versions/manifest/6/7/c149d8f119b951e46b1e7d16c25facb7ce2ad4/1.20-pre6.json"
    },
    {
      "assetHash": "fcc539e68fc40b9e89708f245468dd58e66fe35d",
      "assetIndex": "5",
      "downloads": "c12f1382c12813fd8bfc7395234f3d0573752387",
      "downloadsId": 1,
      "hash": "6aeec9861c775d2ba17e50c2b03069db4e81dd41",
      "lastModified": "2023-06-07T12:41:40+00:00",
      "time": "2023-05-25T12:22:00+00:00",
      "type": "snapshot",
      "url": "https://skyrising.github.io/mc-versions/manifest/6/a/eec9861c775d2ba17e50c2b03069db4e81dd41/1.20-pre6.json"
    },
    {
      "assetHash": "64b9fd8ed2e4529090adadf837e90f030f70d32c",
      "assetIndex": "5",
      "downloads": "c12f1382c12813fd8bfc7395234f3d0573752387",
      "downloadsId": 1,
      "hash": "b786cc683bbc437a8d9267d8415bdbfdab8e56d1",
      "lastModified": "2023-06-01T12:32:11+00:00",
      "time": "2023-05-25T12:22:00+00:00",
      "type": "snapshot",
      "url": "https://skyrising.github.io/mc-versions/manifest/b/7/86cc683bbc437a8d9267d8415bdbfdab8e56d1/1.20-pre6.json"
    },
    {
      "assetHash": "2d635f15e68577a15c19f6a8ac9b74c9919bb7da",
      "assetIndex": "5",
      "downloads": "c12f1382c12813fd8bfc7395234f3d0573752387",
      "downloadsId": 1,
      "hash": "9682c1c4236efa3fbd3264ff7505a47739c652df",
      "lastModified": "2023-05-31T12:43:04+00:00",
      "time": "2023-05-25T12:22:00+00:00",
      "type": "snapshot",
      "url": "https://skyrising.github.io/mc-versions/manifest/9/6/82c1c4236efa3fbd3264ff7505a47739c652df/1.20-pre6.json"
    },
    {
      "assetHash": "f81321f7b11e718207af154e7661221797c07905",
      "assetIndex": "5",
      "downloads": "c12f1382c12813fd8bfc7395234f3d0573752387",
      "downloadsId": 1,
      "hash": "45dec27fd11c078c4c780fd96ed8d6116696cc24",
      "lastModified": "2023-05-29T14:03:39+00:00",
      "time": "2023-05-25T12:22:00+00:00",
      "type": "snapshot",
      "url": "https://skyrising.github.io/mc-versions/manifest/4/5/dec27fd11c078c4c780fd96ed8d6116696cc24/1.20-pre6.json"
    },
    {
      "assetHash": "278637636de8d01413e4c3d1824ddb34f91e3187",
      "assetIndex": "5",
      "downloads": "c12f1382c12813fd8bfc7395234f3d0573752387",
      "downloadsId": 1,
      "hash": "09c96f8ecf2cbe659805c12f6834d148c1d667be",
      "lastModified": "2023-05-25T12:30:31+00:00",
      "time": "2023-05-25T12:22:00+00:00",
      "type": "snapshot",
      "url": "https://skyrising.github.io/mc-versions/manifest/0/9/c96f8ecf2cbe659805c12f6834d148c1d667be/1.20-pre6.json"
    }
  ],
  "next": [
    "1.20-pre7"
  ],
  "normalizedVersion": "1.20.0-pre.6",
  "previous": [
    "1.20-pre5"
  ],
  "protocol": {
    "type": "netty-snapshot",
    "version": 139
  },
  "releaseTarget": "1.20",
  "releaseTime": "2023-05-25T12:22:00+00:00",
  "server": true,
  "sharedMappings": true,
  "world": {
    "format": "anvil",
    "version": 3460
  }
}