{
  "$schema": "https://skyrising.github.io/mc-versions/schemas/version.json",
  "client": true,
  "displayVersion": "26.1 Snapshot 7",
  "downloads": {
    "client": {
      "sha1": "ada715d3943e7584f04aca8ec44f5d3cd767353a",
      "size": 37841491,
      "url": "https://piston-data.mojang.com/v1/objects/ada715d3943e7584f04aca8ec44f5d3cd767353a/client.jar"
    },
    "server": {
      "sha1": "d3b86d840aa59a7512b6a028d40762cf6e492eeb",
      "size": 60329242,
      "url": "https://piston-data.mojang.com/v1/objects/d3b86d840aa59a7512b6a028d40762cf6e492eeb/server.jar"
    }
  },
  "id": "26.1-snapshot-7",
  "libraries": [
    "at.yawk.lz4:lz4-java:1.10.1",
    "com.azure:azure-json:1.4.0",
    "com.github.oshi:oshi-core:6.9.0",
    "com.google.code.gson:gson:2.13.2",
    "com.google.guava:failureaccess:1.0.3",
    "com.google.guava:guava:33.5.0-jre",
    "com.ibm.icu:icu4j:77.1",
    "com.microsoft.azure:msal4j:1.23.1",
    "com.mojang:authlib:7.0.62",
    "com.mojang:blocklist:1.0.10",
    "com.mojang:brigadier:1.3.10",
    "com.mojang:datafixerupper:9.0.19",
    "com.mojang:jtracy:1.0.37",
    "com.mojang:logging:1.6.11",
    "com.mojang:patchy:2.2.10",
    "com.mojang:text2speech:1.18.11",
    "commons-codec:commons-codec:1.19.0",
    "commons-io:commons-io:2.20.0",
    "io.netty:netty-buffer:4.2.7.Final",
    "io.netty:netty-codec-base:4.2.7.Final",
    "io.netty:netty-codec-compression:4.2.7.Final",
    "io.netty:netty-codec-http:4.2.7.Final",
    "io.netty:netty-common:4.2.7.Final",
    "io.netty:netty-handler:4.2.7.Final",
    "io.netty:netty-resolver:4.2.7.Final",
    "io.netty:netty-transport-classes-epoll:4.2.7.Final",
    "io.netty:netty-transport-classes-kqueue:4.2.7.Final",
    "io.netty:netty-transport-native-unix-common:4.2.7.Final",
    "io.netty:netty-transport:4.2.7.Final",
    "it.unimi.dsi:fastutil:8.5.18",
    "net.java.dev.jna:jna-platform:5.17.0",
    "net.java.dev.jna:jna:5.17.0",
    "net.sf.jopt-simple:jopt-simple:5.0.4",
    "org.apache.commons:commons-compress:1.28.0",
    "org.apache.commons:commons-lang3:3.19.0",
    "org.apache.logging.log4j:log4j-api:2.25.2",
    "org.apache.logging.log4j:log4j-core:2.25.2",
    "org.apache.logging.log4j:log4j-slf4j2-impl:2.25.2",
    "org.jcraft:jorbis:0.0.17",
    "org.joml:joml:1.10.8",
    "org.jspecify:jspecify:1.0.0",
    "org.lwjgl:lwjgl-freetype:3.3.3",
    "org.lwjgl:lwjgl-glfw:3.3.3",
    "org.lwjgl:lwjgl-jemalloc:3.3.3",
    "org.lwjgl:lwjgl-openal:3.3.3",
    "org.lwjgl:lwjgl-opengl:3.3.3",
    "org.lwjgl:lwjgl-stb:3.3.3",
    "org.lwjgl:lwjgl-tinyfd:3.3.3",
    "org.lwjgl:lwjgl:3.3.3",
    "org.slf4j:slf4j-api:2.0.17"
  ],
  "manifests": [
    {
      "assetHash": "a297059424dfafc8402646b1e8cdea8de2cc9500",
      "assetIndex": "30",
      "downloads": "d628a22bcb55b2251c42fff2d79338b3f396dbea",
      "downloadsId": 1,
      "hash": "79c494333c8e9d7822fb5bbe998b8bc820c9a5ba",
      "lastModified": "2026-04-28T12:54:54+00:00",
      "time": "2026-02-11T09:25:36+00:00",
      "type": "snapshot",
      "url": "../manifest/7/9/c494333c8e9d7822fb5bbe998b8bc820c9a5ba/26.1-snapshot-7.json"
    },
    {
      "assetHash": "2dad34d87825936f854ddd15c41b9732a9f183b0",
      "assetIndex": "30",
      "downloads": "d628a22bcb55b2251c42fff2d79338b3f396dbea",
      "downloadsId": 1,
      "hash": "136fb8433ae748cf74f1491de7f4c7a56f3c9f27",
      "lastModified": "2026-04-21T12:13:25+00:00",
      "time": "2026-02-11T09:25:36+00:00",
      "type": "snapshot",
      "url": "../manifest/1/3/6fb8433ae748cf74f1491de7f4c7a56f3c9f27/26.1-snapshot-7.json"
    },
    {
      "assetHash": "079069a1fe7d4a5873fc22949aa4a1daeb005816",
      "assetIndex": "30",
      "downloads": "d628a22bcb55b2251c42fff2d79338b3f396dbea",
      "downloadsId": 1,
      "hash": "c4af85ad5cbc162644bb009a573bb0e211060509",
      "lastModified": "2026-04-14T11:42:06+00:00",
      "time": "2026-02-11T09:25:36+00:00",
      "type": "snapshot",
      "url": "../manifest/c/4/af85ad5cbc162644bb009a573bb0e211060509/26.1-snapshot-7.json"
    },
    {
      "assetHash": "77755c06f803fbc30617870e64fa70df435bc09d",
      "assetIndex": "30",
      "downloads": "d628a22bcb55b2251c42fff2d79338b3f396dbea",
      "downloadsId": 1,
      "hash": "db109d2923c9709ac723ba9430469167604fd34c",
      "lastModified": "2026-04-09T10:53:03+00:00",
      "time": "2026-02-11T09:25:36+00:00",
      "type": "snapshot",
      "url": "../manifest/d/b/109d2923c9709ac723ba9430469167604fd34c/26.1-snapshot-7.json"
    },
    {
      "assetHash": "9cab977ba76deb72fad9995b02f25cf3326eedd0",
      "assetIndex": "30",
      "downloads": "d628a22bcb55b2251c42fff2d79338b3f396dbea",
      "downloadsId": 1,
      "hash": "4264ac016c66d3546dd3fc093a95663c601d419c",
      "lastModified": "2026-04-08T12:54:39+00:00",
      "time": "2026-02-11T09:25:36+00:00",
      "type": "snapshot",
      "url": "../manifest/4/2/64ac016c66d3546dd3fc093a95663c601d419c/26.1-snapshot-7.json"
    },
    {
      "assetHash": "92e5fb3b14fb0ea77d405e35bd94e0fb2428d485",
      "assetIndex": "30",
      "downloads": "d628a22bcb55b2251c42fff2d79338b3f396dbea",
      "downloadsId": 1,
      "hash": "05656afbb40d61331c5a66ee50e383e39ac986fd",
      "lastModified": "2026-04-07T12:03:54+00:00",
      "time": "2026-02-11T09:25:36+00:00",
      "type": "snapshot",
      "url": "../manifest/0/5/656afbb40d61331c5a66ee50e383e39ac986fd/26.1-snapshot-7.json"
    },
    {
      "assetHash": "3226889d57b84eb26553582b6ad60781db949944",
      "assetIndex": "30",
      "downloads": "d628a22bcb55b2251c42fff2d79338b3f396dbea",
      "downloadsId": 1,
      "hash": "dd617e898d1dae717a2d4ab03f1cfd4cfdd9a75d",
      "lastModified": "2026-04-01T09:16:48+00:00",
      "time": "2026-02-11T09:25:36+00:00",
      "type": "snapshot",
      "url": "../manifest/d/d/617e898d1dae717a2d4ab03f1cfd4cfdd9a75d/26.1-snapshot-7.json"
    },
    {
      "assetHash": "3c9d3d234d853c3f0b982fd64fa5c7a7de55f123",
      "assetIndex": "30",
      "downloads": "d628a22bcb55b2251c42fff2d79338b3f396dbea",
      "downloadsId": 1,
      "hash": "77dde0c1e290c71950ba890e4aa0f69ce60237a5",
      "lastModified": "2026-03-31T11:07:42+00:00",
      "time": "2026-02-11T09:25:36+00:00",
      "type": "snapshot",
      "url": "../manifest/7/7/dde0c1e290c71950ba890e4aa0f69ce60237a5/26.1-snapshot-7.json"
    },
    {
      "assetHash": "a1969c2dd99745486cbd873da16792b3b2381504",
      "assetIndex": "30",
      "downloads": "d628a22bcb55b2251c42fff2d79338b3f396dbea",
      "downloadsId": 1,
      "hash": "76d0c9c2641abffd0aa6b4859bbb8a5bd3166685",
      "lastModified": "2026-03-24T12:33:35+00:00",
      "time": "2026-02-11T09:25:36+00:00",
      "type": "snapshot",
      "url": "../manifest/7/6/d0c9c2641abffd0aa6b4859bbb8a5bd3166685/26.1-snapshot-7.json"
    },
    {
      "assetHash": "9f7699c06a12a302eb26991538e3a0bc2b27c33c",
      "assetIndex": "30",
      "downloads": "d628a22bcb55b2251c42fff2d79338b3f396dbea",
      "downloadsId": 1,
      "hash": "e6714416cdd0e2d01143b02709c2a7b121fc26ac",
      "lastModified": "2026-03-23T12:07:15+00:00",
      "time": "2026-02-11T09:25:36+00:00",
      "type": "snapshot",
      "url": "../manifest/e/6/714416cdd0e2d01143b02709c2a7b121fc26ac/26.1-snapshot-7.json"
    },
    {
      "assetHash": "cda207d093042ce10a65a5539a9e6c9e5712a14a",
      "assetIndex": "30",
      "downloads": "d628a22bcb55b2251c42fff2d79338b3f396dbea",
      "downloadsId": 1,
      "hash": "4c4143a9dbdb1bfeddc4e33ba47a39d48b9a8227",
      "lastModified": "2026-03-20T10:28:16+00:00",
      "time": "2026-02-11T09:25:36+00:00",
      "type": "snapshot",
      "url": "../manifest/4/c/4143a9dbdb1bfeddc4e33ba47a39d48b9a8227/26.1-snapshot-7.json"
    },
    {
      "assetHash": "084f6aa69256b51cc1aae6d2ff90f0271c03500f",
      "assetIndex": "30",
      "downloads": "d628a22bcb55b2251c42fff2d79338b3f396dbea",
      "downloadsId": 1,
      "hash": "c62d7942ea3f718b1882c092a6978ec74cd492d7",
      "lastModified": "2026-03-19T14:57:24+00:00",
      "time": "2026-02-11T09:25:36+00:00",
      "type": "snapshot",
      "url": "../manifest/c/6/2d7942ea3f718b1882c092a6978ec74cd492d7/26.1-snapshot-7.json"
    },
    {
      "assetHash": "c8333b47188ea66834801ea69434d65e3abebe6c",
      "assetIndex": "30",
      "downloads": "d628a22bcb55b2251c42fff2d79338b3f396dbea",
      "downloadsId": 1,
      "hash": "dcc04b31e08d82bee19356fc2a975eb57b6937bd",
      "lastModified": "2026-03-17T14:02:06+00:00",
      "time": "2026-02-11T09:25:36+00:00",
      "type": "snapshot",
      "url": "../manifest/d/c/c04b31e08d82bee19356fc2a975eb57b6937bd/26.1-snapshot-7.json"
    },
    {
      "assetHash": "986e9ea6b69a981d90005601047d420902862d5c",
      "assetIndex": "30",
      "downloads": "d628a22bcb55b2251c42fff2d79338b3f396dbea",
      "downloadsId": 1,
      "hash": "1f21dbe07e1c29428ca693c3e2add87694d3b99d",
      "lastModified": "2026-03-13T13:14:35+00:00",
      "time": "2026-02-11T09:25:36+00:00",
      "type": "snapshot",
      "url": "../manifest/1/f/21dbe07e1c29428ca693c3e2add87694d3b99d/26.1-snapshot-7.json"
    },
    {
      "assetHash": "45cf9264bd5c098adac408ae0bb977595d789455",
      "assetIndex": "30",
      "downloads": "d628a22bcb55b2251c42fff2d79338b3f396dbea",
      "downloadsId": 1,
      "hash": "259d89f0c72bbdc757a24ba10c04357764f6867f",
      "lastModified": "2026-03-10T13:20:12+00:00",
      "time": "2026-02-11T09:25:36+00:00",
      "type": "snapshot",
      "url": "../manifest/2/5/9d89f0c72bbdc757a24ba10c04357764f6867f/26.1-snapshot-7.json"
    },
    {
      "assetHash": "1a3d9b29e810e02f60800c1cb180c1d0891940d2",
      "assetIndex": "30",
      "downloads": "d628a22bcb55b2251c42fff2d79338b3f396dbea",
      "downloadsId": 1,
      "hash": "158b69769a09bc75c33976b28f0a40e66ab7f2f3",
      "lastModified": "2026-03-03T13:10:22+00:00",
      "time": "2026-02-11T09:25:36+00:00",
      "type": "snapshot",
      "url": "../manifest/1/5/8b69769a09bc75c33976b28f0a40e66ab7f2f3/26.1-snapshot-7.json"
    },
    {
      "assetHash": "9b3b79c3e43d6ea73dfdd960681a30be97b4273a",
      "assetIndex": "30",
      "downloads": "d628a22bcb55b2251c42fff2d79338b3f396dbea",
      "downloadsId": 1,
      "hash": "7c7fc2d7ba3e5880464d2d2c28cfe842ea2bc5ee",
      "lastModified": "2026-02-24T13:11:13+00:00",
      "time": "2026-02-11T09:25:36+00:00",
      "type": "snapshot",
      "url": "../manifest/7/c/7fc2d7ba3e5880464d2d2c28cfe842ea2bc5ee/26.1-snapshot-7.json"
    },
    {
      "assetHash": "7bc99875405c40763696cf7e89cefcc7faaa5d6b",
      "assetIndex": "30",
      "downloads": "d628a22bcb55b2251c42fff2d79338b3f396dbea",
      "downloadsId": 1,
      "hash": "e536918dd5b85b20f9ff20d7fe44ffe4984306bf",
      "lastModified": "2026-02-18T10:21:12+00:00",
      "time": "2026-02-11T09:25:36+00:00",
      "type": "snapshot",
      "url": "../manifest/e/5/36918dd5b85b20f9ff20d7fe44ffe4984306bf/26.1-snapshot-7.json"
    },
    {
      "assetHash": "61b6f37ff039c2cd3f70ad458a293323aa50105a",
      "assetIndex": "30",
      "downloads": "d628a22bcb55b2251c42fff2d79338b3f396dbea",
      "downloadsId": 1,
      "hash": "ee8180d05ce54494b1ea920e00c93b6a89168d96",
      "lastModified": "2026-02-17T12:49:26+00:00",
      "time": "2026-02-11T09:25:36+00:00",
      "type": "snapshot",
      "url": "../manifest/e/e/8180d05ce54494b1ea920e00c93b6a89168d96/26.1-snapshot-7.json"
    },
    {
      "assetHash": "4f52d7906ece3d6600326aebf850113698dc8423",
      "assetIndex": "30",
      "downloads": "d628a22bcb55b2251c42fff2d79338b3f396dbea",
      "downloadsId": 1,
      "hash": "2b46ba3d2a86d104a05adaef10ab3c621840bad4",
      "lastModified": "2026-02-11T09:32:15+00:00",
      "time": "2026-02-11T09:25:36+00:00",
      "type": "snapshot",
      "url": "../manifest/2/b/46ba3d2a86d104a05adaef10ab3c621840bad4/26.1-snapshot-7.json"
    }
  ],
  "next": [
    "26.1-snapshot-8"
  ],
  "normalizedVersion": "26.1.0-alpha.7",
  "previous": [
    "26.1-snapshot-6"
  ],
  "protocol": {
    "type": "netty-snapshot",
    "version": 293
  },
  "releaseTarget": "26.1",
  "releaseTime": "2026-02-11T09:25:36+00:00",
  "server": true,
  "type": "snapshot",
  "unobfuscated": true,
  "world": {
    "format": "anvil",
    "version": 4775
  }
}